[
  {
    "id": "19d6d47fd37tri58",
    "text": "111",
    "completed": false,
    "date": "2026-04-08"
  },
  {
    "id": "t1",
    "text": "模糊一点，预付模式",
    "completed": false,
    "date": "2026-04-08"
  },
  {
    "id": "t2",
    "text": "编剧合同的结算条款",
    "completed": false,
    "date": "2026-04-08"
  },
  {
    "id": "t3",
    "text": "唯一部老剧，是不是要调整结算规则",
    "completed": false,
    "date": "2026-04-08"
  },
  {
    "id": "t4",
    "text": "作者向的，要出公告，而不是补协",
    "completed": false,
    "date": "2026-04-08"
  },
  {
    "id": "t5",
    "text": "再传一下原始账单名称",
    "completed": false,
    "date": "2026-04-08"
  },
  {
    "id": "t6",
    "text": "杨水星的特殊分成比例邮件，单独处理",
    "completed": false,
    "date": "2026-04-08"
  },
  {
    "id": "t7",
    "text": "762623460461720568​1（相关事项跟进）",
    "completed": false,
    "date": "2026-04-08"
  },
  {
    "id": "t8",
    "text": "微信分销感觉有问题，取不到",
    "completed": false,
    "date": "2026-04-08"
  },
  {
    "id": "t9",
    "text": "千锻一品加个AC",
    "completed": false,
    "date": "2026-04-08"
  },
  {
    "id": "t10",
    "text": "推小果只结算到331",
    "completed": false,
    "date": "2026-04-08"
  },
  {
    "id": "t11",
    "text": "CP发送结算单",
    "completed": false,
    "date": "2026-04-08"
  }
]